{
  "ComponentIndexes": {},
  "ControlUniqueGuids": {},
  "ControlUniqueIds": {
    "App": 1,
    "ConfigurationScreen": 9,
    "drpGoogleMaptypes": 20,
    "HomeScreen": 3,
    "Image1": 29,
    "Image4": 5,
    "Image5": 4,
    "imgMapControl": 15,
    "Label1": 6,
    "Label2": 7,
    "Label4": 21,
    "Label4_1": 24,
    "latitude": 32,
    "lblGPSLocation": 25,
    "lblGPSLocation_1": 17,
    "lblGPSLocation_2": 19,
    "longitude": 33,
    "MainScreen": 14,
    "Rectangle1": 16,
    "Rectangle1_1": 22,
    "Screen1": 27,
    "slZoom": 23,
    "Start": 8,
    "tglGPSLocation": 35,
    "Timer1": 28,
    "txtGoogleMapsID": 13,
    "txtGoogleMapsKey": 10,
    "txtImageHeight": 12,
    "txtImageWidth": 11,
    "txtLocation": 18
  },
  "FunctionParamsInvariantScripts": {},
  "FunctionParamsInvariantScriptsOnInstances": {},
  "HeaderLastSavedDateTimeUTC": "11/12/2022 14:55:02",
  "IsLegacyComponentAllowGlobalScopeCase": false,
  "LocalConnectionIDReferences": {},
  "LocalDatabaseReferencesAsEmpty": false,
  "LocalResourceFileNames": {
    "Oshen design 1": "7c12212e-93d7-4792-926d-f13eb1659ce5.png",
    "Oshen logo": "44eb56bf-c624-4ec0-ab4b-518c7bcf2a68.png"
  },
  "LocalResourceRootPaths": {
    "Oshen design 1": "https://docserverpwaprodsin.blob.core.windows.net/a4342c48-4ee6-4e5f-b2b3-49296b856cfe-1/resource/Assets0Images07c12212e-93d7-4792-926d-f13eb1659ce5.png?sv=2017-04-17&sr=b&sig=flKXqy8ZmxY%2BpiTcuq08qp4xXwdeGNCtwGCa7Ga%2B0Dg%3D&spr=https&se=2022-11-13T12%3A56%3A03Z&sp=r",
    "Oshen logo": "https://docserverpwaprodsin.blob.core.windows.net/a4342c48-4ee6-4e5f-b2b3-49296b856cfe-1/resource/Assets0Images044eb56bf-c624-4ec0-ab4b-518c7bcf2a68.png?sv=2017-04-17&sr=b&sig=k%2Fo2cKF9oyVS8D%2BlzlYLoHKAF6E%2BJz8H7OenP8mC8pI%3D&spr=https&se=2022-11-13T12%3A56%3A03Z&sp=r"
  },
  "OldLogoFileName": "bag0wvqm.jpg",
  "OrderComponentMetadata": {},
  "OrderComponentTemplate": {},
  "OrderDataSource": {
    "DropDownSample": 0
  },
  "OrderGroupControls": {},
  "OrderPcfTemplate": {},
  "OrderTemplate": {},
  "OrderXMLTemplate": {
    "button": 2,
    "dropdown": 5,
    "image": 0,
    "label": 1,
    "rectangle": 4,
    "slider": 6,
    "text": 3,
    "timer": 8,
    "toggleSwitch": 7
  },
  "PublishOrderIndices": {
    "App": 0,
    "ConfigurationScreen": 0,
    "drpGoogleMaptypes": 12,
    "HomeScreen": 0,
    "Image1": 1,
    "Image4": 3,
    "Image5": 2,
    "imgMapControl": 7,
    "Label1": 4,
    "Label2": 5,
    "Label4": 13,
    "Label4_1": 16,
    "latitude": 23,
    "lblGPSLocation": 17,
    "lblGPSLocation_1": 9,
    "lblGPSLocation_2": 11,
    "longitude": 24,
    "MainScreen": 0,
    "Rectangle1": 8,
    "Rectangle1_1": 14,
    "Screen1": 0,
    "slZoom": 15,
    "Start": 6,
    "tglGPSLocation": 18,
    "Timer1": 0,
    "txtGoogleMapsID": 22,
    "txtGoogleMapsKey": 19,
    "txtImageHeight": 21,
    "txtImageWidth": 20,
    "txtLocation": 10
  },
  "ResourcesJsonIndices": {
    "Image-Oshen design 1": 2,
    "Image-Oshen logo": 1,
    "Image-SampleImage": 0
  },
  "RuleScreenIdWithoutScreen": {},
  "TemplateVersions": {},
  "VolatileProperties": {
    "AnalysisLoadTime": 0.2100921,
    "ControlCount": {
      "button": 1,
      "dropdown": 1,
      "image": 4,
      "label": 8,
      "rectangle": 2,
      "screen": 4,
      "slider": 1,
      "text": 6,
      "timer": 1,
      "toggleSwitch": 1
    },
    "DeserializationLoadTime": 1.0245414,
    "ErrorCount": 0
  },
  "WasLocalDatabaseReferencesEmpty": true
}